src/pixel_counters .v
module pixel_counters (
    input wire        pixel_clk,      
    input wire        rst_n,          
    input wire [11:0] h_total,        
    input wire [11:0] v_total,        
    output reg [11:0] h_count,        
    output reg [11:0] v_count,        
    output reg        frame_start     
);

// Évite les modulos coûteux - utilise des comparaisons
always @(posedge pixel_clk or negedge rst_n) begin
    if (!rst_n) begin
        h_count <= 12'd0;
        v_count <= 12'd0;
        frame_start <= 1'b0;
    end else begin
        // Compteur horizontal
        if (h_count >= h_total - 1) begin
            h_count <= 12'd0;
            
            // Compteur vertical
            if (v_count >= v_total - 1) begin
                v_count <= 12'd0;
                frame_start <= 1'b1;  // Début de nouvelle trame
            end else begin
                v_count <= v_count + 1;
                frame_start <= 1'b0;
            end
        end else begin
            h_count <= h_count + 1;
            frame_start <= 1'b0;
        end
    end
end


endmodule

testbench/tb_pixel_counters_vscode.v
module tb_pixel_counters_vscode;
    // Signaux
    reg clk = 0;
    reg rst_n = 0;
    wire [11:0] h_count, v_count;
    wire frame_start;
    
    // Instance
    pixel_counters dut (
        .pixel_clk(clk),
        .rst_n(rst_n), 
        .h_total(12'd10),
        .v_total(12'd5),
        .h_count(h_count),
        .v_count(v_count),
        .frame_start(frame_start)
    );
    
    // Horloge
    always #5 clk = ~clk;
    
    // Test
    initial begin
        // Pour GTKWave
        $dumpfile("waves.vcd");
        $dumpvars(0, tb_pixel_counters_vscode);
        
        // Test
        $display("=== VSCode + Icarus Test ===");
        rst_n = 0; #50; rst_n = 1;
        
        repeat (100) @(posedge clk);
        
        $display("=== Test Complete ===");
        $finish;
    end
    
    // Monitoring
    always @(posedge clk) begin
        if ($time % 100 == 0)
            $display("t=%0t: H=%d V=%d F=%b", $time, h_count, v_count, frame_start);
    end
endmodule

testbench/waves.vcd
$date
	Sat Sep 13 14:21:24 2025
$end
$version
	Icarus Verilog
$end
$timescale
	1s
$end
$scope module tb_pixel_counters_vscode $end
$var wire 12 ! v_count [11:0] $end
$var wire 12 " h_count [11:0] $end
$var wire 1 # frame_start $end
$var reg 1 $ clk $end
$var reg 1 % rst_n $end
$scope module dut $end
$var wire 12 & h_total [11:0] $end
$var wire 1 $ pixel_clk $end
$var wire 1 % rst_n $end
$var wire 12 ' v_total [11:0] $end
$var reg 1 # frame_start $end
$var reg 12 ( h_count [11:0] $end
$var reg 12 ) v_count [11:0] $end
$upscope $end
$upscope $end
$enddefinitions $end
#0
$dumpvars
b0 )
b0 (
b101 '
b1010 &
0%
0$
0#
b0 "
b0 !
$end
#5
1$
#10
0$
#15
1$
#20
0$
#25
1$
#30
0$
#35
1$
#40
0$
#45
1$
#50
0$
1%
#55
b1 "
b1 (
1$
#60
0$
#65
b10 "
b10 (
1$
#70
0$
#75
b11 "
b11 (
1$
#80
0$
#85
b100 "
b100 (
1$
#90
0$
#95
b101 "
b101 (
1$
#100
0$
#105
b110 "
b110 (
1$
#110
0$
#115
b111 "
b111 (
1$
#120
0$
#125
b1000 "
b1000 (
1$
#130
0$
#135
b1001 "
b1001 (
1$
#140
0$
#145
b1 !
b1 )
b0 "
b0 (
1$
#150
0$
#155
b1 "
b1 (
1$
#160
0$
#165
b10 "
b10 (
1$
#170
0$
#175
b11 "
b11 (
1$
#180
0$
#185
b100 "
b100 (
1$
#190
0$
#195
b101 "
b101 (
1$
#200
0$
#205
b110 "
b110 (
1$
#210
0$
#215
b111 "
b111 (
1$
#220
0$
#225
b1000 "
b1000 (
1$
#230
0$
#235
b1001 "
b1001 (
1$
#240
0$
#245
b10 !
b10 )
b0 "
b0 (
1$
#250
0$
#255
b1 "
b1 (
1$
#260
0$
#265
b10 "
b10 (
1$
#270
0$
#275
b11 "
b11 (
1$
#280
0$
#285
b100 "
b100 (
1$
#290
0$
#295
b101 "
b101 (
1$
#300
0$
#305
b110 "
b110 (
1$
#310
0$
#315
b111 "
b111 (
1$
#320
0$
#325
b1000 "
b1000 (
1$
#330
0$
#335
b1001 "
b1001 (
1$
#340
0$
#345
b11 !
b11 )
b0 "
b0 (
1$
#350
0$
#355
b1 "
b1 (
1$
#360
0$
#365
b10 "
b10 (
1$
#370
0$
#375
b11 "
b11 (
1$
#380
0$
#385
b100 "
b100 (
1$
#390
0$
#395
b101 "
b101 (
1$
#400
0$
#405
b110 "
b110 (
1$
#410
0$
#415
b111 "
b111 (
1$
#420
0$
#425
b1000 "
b1000 (
1$
#430
0$
#435
b1001 "
b1001 (
1$
#440
0$
#445
b100 !
b100 )
b0 "
b0 (
1$
#450
0$
#455
b1 "
b1 (
1$
#460
0$
#465
b10 "
b10 (
1$
#470
0$
#475
b11 "
b11 (
1$
#480
0$
#485
b100 "
b100 (
1$
#490
0$
#495
b101 "
b101 (
1$
#500
0$
#505
b110 "
b110 (
1$
#510
0$
#515
b111 "
b111 (
1$
#520
0$
#525
b1000 "
b1000 (
1$
#530
0$
#535
b1001 "
b1001 (
1$
#540
0$
#545
1#
b0 !
b0 )
b0 "
b0 (
1$
#550
0$
#555
0#
b1 "
b1 (
1$
#560
0$
#565
b10 "
b10 (
1$
#570
0$
#575
b11 "
b11 (
1$
#580
0$
#585
b100 "
b100 (
1$
#590
0$
#595
b101 "
b101 (
1$
#600
0$
#605
b110 "
b110 (
1$
#610
0$
#615
b111 "
b111 (
1$
#620
0$
#625
b1000 "
b1000 (
1$
#630
0$
#635
b1001 "
b1001 (
1$
#640
0$
#645
b1 !
b1 )
b0 "
b0 (
1$
#650
0$
#655
b1 "
b1 (
1$
#660
0$
#665
b10 "
b10 (
1$
#670
0$
#675
b11 "
b11 (
1$
#680
0$
#685
b100 "
b100 (
1$
#690
0$
#695
b101 "
b101 (
1$
#700
0$
#705
b110 "
b110 (
1$
#710
0$
#715
b111 "
b111 (
1$
#720
0$
#725
b1000 "
b1000 (
1$
#730
0$
#735
b1001 "
b1001 (
1$
#740
0$
#745
b10 !
b10 )
b0 "
b0 (
1$
#750
0$
#755
b1 "
b1 (
1$
#760
0$
#765
b10 "
b10 (
1$
#770
0$
#775
b11 "
b11 (
1$
#780
0$
#785
b100 "
b100 (
1$
#790
0$
#795
b101 "
b101 (
1$
#800
0$
#805
b110 "
b110 (
1$
#810
0$
#815
b111 "
b111 (
1$
#820
0$
#825
b1000 "
b1000 (
1$
#830
0$
#835
b1001 "
b1001 (
1$
#840
0$
#845
b11 !
b11 )
b0 "
b0 (
1$
#850
0$
#855
b1 "
b1 (
1$
#860
0$
#865
b10 "
b10 (
1$
#870
0$
#875
b11 "
b11 (
1$
#880
0$
#885
b100 "
b100 (
1$
#890
0$
#895
b101 "
b101 (
1$
#900
0$
#905
b110 "
b110 (
1$
#910
0$
#915
b111 "
b111 (
1$
#920
0$
#925
b1000 "
b1000 (
1$
#930
0$
#935
b1001 "
b1001 (
1$
#940
0$
#945
b100 !
b100 )
b0 "
b0 (
1$
#950
0$
#955
b1 "
b1 (
1$
#960
0$
#965
b10 "
b10 (
1$
#970
0$
#975
b11 "
b11 (
1$
#980
0$
#985
b100 "
b100 (
1$
#990
0$
#995
b101 "
b101 (
1$
#1000
0$
#1005
b110 "
b110 (
1$
#1010
0$
#1015
b111 "
b111 (
1$
#1020
0$
#1025
b1000 "
b1000 (
1$
#1030
0$
#1035
b1001 "
b1001 (
1$
#1040
0$
#1045
1#
b0 !
b0 )
b0 "
b0 (
1$
